llm_input_sanitizer/__init__.py
llm_input_sanitizer/sanitizer.py
llm_input_sanitizer/utils.py
llm_input_sanitizer-0.2.1.dist-info/licenses/LICENSE
tests/__init__.py
tests/test_advanced_sanitizer.py
tests/test_sanitizer.py
llm_input_sanitizer-0.2.1.dist-info/METADATA
llm_input_sanitizer-0.2.1.dist-info/WHEEL
llm_input_sanitizer-0.2.1.dist-info/top_level.txt
llm_input_sanitizer-0.2.1.dist-info/RECORD
